setup.cfg
setup.py
steam_market/__init__.py
steam_market/steam_market.py
steam_market.egg-info/PKG-INFO
steam_market.egg-info/SOURCES.txt
steam_market.egg-info/dependency_links.txt
steam_market.egg-info/top_level.txt